ocean_leonid/__init__.py
ocean_leonid/src/__init__.py
ocean_leonid/src/apis.py
ocean_leonid/src/exceptions.py
ocean_leonid/src/layout.py
ocean_leonid-0.1.0.dist-info/METADATA
ocean_leonid-0.1.0.dist-info/WHEEL
ocean_leonid-0.1.0.dist-info/RECORD
