Metadata-Version: 2.1
Name: ocean-leonid
Version: 0.1.0
Summary: 
Author: Robert Lawrence
Requires-Python: >=3.11,<4.0
Classifier: Programming Language :: Python :: 3
Classifier: Programming Language :: Python :: 3.11
Requires-Dist: dash (>=2.12.1,<3.0.0)
Requires-Dist: pandas (>=2.0.3,<3.0.0)
Requires-Dist: requests (>=2.31.0,<3.0.0)
